las_py/__init__.py
las_py/laspy.py
las_py-1.1.0.dist-info/LICENSE
las_py-1.1.0.dist-info/METADATA
las_py-1.1.0.dist-info/WHEEL
las_py-1.1.0.dist-info/top_level.txt
las_py-1.1.0.dist-info/RECORD
