Metadata-Version: 2.1
Name: las-py
Version: 1.1.0
Summary: A zero-dependency python library for reading/parsing canadian well-log files (.Las files)
Home-page: https://github.com/iykekings/las_py
Author: Ikechukwu Eze
Author-email: iykekings36@gmail.com
License: UNKNOWN
Project-URL: Documentation, https://github.com/iykekings/las_py
Project-URL: Funding, https://www.patreon.com/bePatron?u=19152008
Project-URL: Source, https://github.com/iykekings/las_py
Project-URL: Tracker, https://github.com/iykekings/las_py/issues
Keywords: well log well-log geophysical geophysics las .las
Platform: UNKNOWN
Classifier: Programming Language :: Python :: 3
Classifier: License :: OSI Approved :: MIT License
Classifier: Operating System :: OS Independent
Requires-Python: >=3
